lloom_ai/__init__.py
lloom_ai/concept.py
lloom_ai/concept_induction.py
lloom_ai/llm.py
lloom_ai/prompts.py
lloom_ai/static/index.css
lloom_ai/static/index.js
lloom_ai/static/index_select.css
lloom_ai/static/index_select.js
lloom_ai/workbench.py
lloom_ai-0.1.1.dist-info/METADATA
lloom_ai-0.1.1.dist-info/WHEEL
lloom_ai-0.1.1.dist-info/RECORD
